mainlymarlin_de_toolkit/01-Package-creation.code-workspace
mainlymarlin_de_toolkit/__init__.py
mainlymarlin_de_toolkit/main.py
mainlymarlin_de_toolkit/vm.py
mainlymarlin_de_toolkit-0.1.0.dist-info/METADATA
mainlymarlin_de_toolkit-0.1.0.dist-info/WHEEL
mainlymarlin_de_toolkit-0.1.0.dist-info/entry_points.txt
mainlymarlin_de_toolkit-0.1.0.dist-info/RECORD
